o2_docparser.py
o2_docparser-1.7.dist-info/METADATA
o2_docparser-1.7.dist-info/WHEEL
o2_docparser-1.7.dist-info/top_level.txt
o2_docparser-1.7.dist-info/RECORD
